[
    {
        "created_at":"2015-08-20 12:14:19",
        "updated_at":"2016-01-12 21:01:14",
        "deleted_at":"2017-03-15 14:55:49",
        "deleted":"@@@_0.0",
        "id":"02ca82f2-7e53-4417-8b87-a151825b6985",
        "volume_id":"16321001-194b-45eb-93ea-f32b0eca156b",
        "attached_host":"prime-72",
        "instance_uuid":"7f5b6bcb-247e-4b31-8e6c-135edb2aaa0d",
        "mountpoint":"\/dev\/vdc",
        "attach_time":"2015-01-12 15:54:16",
        "detach_time":"2017-03-15 14:55:49",
        "attach_mode":"rw",
        "attach_status":"detached"
    },
    {
        "created_at":"2015-08-20 12:14:19",
        "updated_at":"2016-06-16 21:41:43",
        "deleted_at":"2017-03-15 14:55:49",
        "deleted":"@@@_2.0",
        "id":"0714b76a-dc69-406e-90bf-500593910ac0",
        "volume_id":"14f87bd2-9e66-4bd0-86bb-df49ae71131e",
        "attached_host":"blitz7-83",
        "instance_uuid":"da448fce-4353-4d1b-86ad-4effa63ec12d",
        "mountpoint":"\/dev\/vda",
        "attach_time":"2015-07-03 13:47:37",
        "detach_time":"2017-03-15 14:55:49",
        "attach_mode":"rw",
        "attach_status":"detached"
    },
    {
        "created_at":"2015-08-20 12:14:19",
        "updated_at":"2016-04-01 20:24:17",
        "deleted_at":"2017-03-15 14:55:49",
        "deleted":"@@@_0.0",
        "id":"08ade0f2-bfd5-4345-8f3d-d098d07b2646",
        "volume_id":"0436e674-a0c0-4dba-b46d-bdddcbe5256d",
        "attached_host":"blitz7-83",
        "instance_uuid":"25b87cb1-2a5a-456b-9eed-c960d2a91dc2",
        "mountpoint":"\/dev\/vda",
        "attach_time":"2015-05-29 18:37:08",
        "detach_time":"2017-03-15 14:55:49",
        "attach_mode":"rw",
        "attach_status":"detached"
    },
    {
        "created_at":"2015-08-20 12:14:19",
        "updated_at":"2016-01-21 21:38:58",
        "deleted_at":"2017-03-15 14:55:49",
        "deleted":"@@@_-1.0",
        "id":"09958f97-7166-425a-aa89-ce0d7b5c824b",
        "volume_id":"bf710c6f-8305-4341-bff6-f186105e1eda",
        "attached_host":"prime-72",
        "instance_uuid":"7bc9f96a-603d-41eb-b0f2-1e01eb091be5",
        "mountpoint":"vda",
        "attach_time":"2014-12-05 18:19:24",
        "detach_time":"2017-03-15 14:55:49",
        "attach_mode":"rw",
        "attach_status":"detached"
    },
    {
        "created_at":"2015-08-20 12:14:19",
        "updated_at":"2015-09-11 20:36:27",
        "deleted_at":"2017-03-15 14:55:49",
        "deleted":"@@@_1.5",
        "id":"0b38b89c-64be-4d4b-86a1-4d681f73c4b0",
        "volume_id":"43fc72c8-0f55-455c-91ed-f3103b6454e2",
        "attached_host":"flare-zenit3",
        "instance_uuid":"57e2e1c0-2ce1-427b-956b-ebec0242f3d2",
        "mountpoint":"\/dev\/vdb",
        "attach_time":"2015-04-13 15:13:20",
        "detach_time":"2017-03-15 14:55:49",
        "attach_mode":"rw",
        "attach_status":"detached"
    },
    {
        "created_at":"2015-08-20 12:14:19",
        "updated_at":"2015-09-11 11:31:03",
        "deleted_at":"2017-03-15 14:55:49",
        "deleted":"@@@_nan",
        "id":"0c6e1c2f-6b05-4afc-868d-70b2dce01f8d",
        "volume_id":"93684471-983d-4d91-8f34-9eebb8b89452",
        "attached_host":"blitz7-83",
        "instance_uuid":"0e9bd913-22a5-4f20-9a1e-3e289ead630e",
        "mountpoint":"\/dev\/vdb",
        "attach_time":"2015-08-11 12:24:22",
        "detach_time":"2017-03-15 14:55:49",
        "attach_mode":"rw",
        "attach_status":"detached"
    },
    {
        "created_at":"2015-08-20 12:14:19",
        "updated_at":"2015-11-19 18:05:40",
        "deleted_at":"2017-03-15 14:55:49",
        "deleted":"@@@_100.0",
        "id":"0df200a8-4346-445c-a63c-f429b796010d",
        "volume_id":"b17da402-802f-4bf3-81ed-24cfac560b98",
        "attached_host":"blitz7-83",
        "instance_uuid":"b4825f40-22e5-4d67-8ba3-957a5b60cd27",
        "mountpoint":"\/dev\/vda",
        "attach_time":"2015-07-10 19:58:10",
        "detach_time":"2017-03-15 14:55:49",
        "attach_mode":"rw",
        "attach_status":"detached"
    },
    {
        "created_at":"2015-08-20 12:14:19",
        "updated_at":"2015-11-25 17:03:20",
        "deleted_at":"2017-03-15 14:55:49",
        "deleted":"@@@_0.1",
        "id":"0e03f24b-1238-4e62-8cf3-fad8bf6fe372",
        "volume_id":"ce863f92-f725-4f10-8804-3502855aabc7",
        "attached_host":"prime-72",
        "instance_uuid":"8a2e7507-ad04-4ed5-b611-2284e0f2ef25",
        "mountpoint":"vda",
        "attach_time":"2015-01-16 02:10:33",
        "detach_time":"2017-03-15 14:55:49",
        "attach_mode":"rw",
        "attach_status":"detached"
    },
    {
        "created_at":"2015-08-20 12:14:19",
        "updated_at":"2016-05-20 20:52:23",
        "deleted_at":"2017-03-15 14:55:49",
        "deleted":"@@@_5.0",
        "id":"1089f94d-d973-4b31-a3f4-c2dbc70ca1ab",
        "volume_id":"2220cfb7-740a-4dd8-8938-f3f3e87f7939",
        "attached_host":"blitz7-83",
        "instance_uuid":"ab505dbc-425f-4c63-8434-7c4db19fe6e2",
        "mountpoint":"\/dev\/vda",
        "attach_time":"2015-06-18 20:41:46",
        "detach_time":"2017-03-15 14:55:49",
        "attach_mode":"rw",
        "attach_status":"detached"
    },
    {
        "created_at":"2015-08-20 12:14:19",
        "updated_at":"2015-08-31 18:13:05",
        "deleted_at":"2017-03-15 14:55:49",
        "deleted":"@@@_0.0",
        "id":"10925cb6-d419-4254-ab7e-6e9763519338",
        "volume_id":"b09f5425-93aa-4c58-a9ea-7ec402a95c84",
        "attached_host":"blitz7-83",
        "instance_uuid":"604b77a0-0727-4de6-ab0a-f624710ff715",
        "mountpoint":"\/dev\/vda",
        "attach_time":"2015-06-10 18:52:41",
        "detach_time":"2017-03-15 14:55:49",
        "attach_mode":"rw",
        "attach_status":"detached"
    },
    {
        "created_at":"2015-08-20 12:14:19",
        "updated_at":"2016-01-25 15:21:19",
        "deleted_at":"2017-03-15 14:55:49",
        "deleted":"@@@_-10.0",
        "id":"12088fa6-4c31-4f97-ac46-ddbdc36700aa",
        "volume_id":"06e4ffda-3a29-4069-a374-f76fc8f080f9",
        "attached_host":"prime-72",
        "instance_uuid":"c013fdde-a964-4dc9-8a22-9c66cf4d5953",
        "mountpoint":"vda",
        "attach_time":"2014-12-04 19:00:18",
        "detach_time":"2017-03-15 14:55:49",
        "attach_mode":"rw",
        "attach_status":"detached"
    },
    {
        "created_at":"2015-08-20 12:14:19",
        "updated_at":"2016-01-21 15:58:35",
        "deleted_at":"2017-03-15 14:55:49",
        "deleted":"@@@_1.01",
        "id":"1395da5f-5237-4782-828d-e63146620a06",
        "volume_id":"26f3fa92-8716-435d-9d51-13751c919023",
        "attached_host":"prime-72",
        "instance_uuid":"89ab9a2b-614e-4349-8c12-391be250e86d",
        "mountpoint":"vda",
        "attach_time":"2014-08-26 13:06:56",
        "detach_time":"2017-03-15 14:55:49",
        "attach_mode":"rw",
        "attach_status":"detached"
    },
    {
        "created_at":"2015-08-20 12:14:19",
        "updated_at":"2015-10-15 09:11:27",
        "deleted_at":"2017-03-15 14:55:49",
        "deleted":"@@@_1000.0",
        "id":"1a81d5f7-3eb8-4ba5-b48c-70c2c94c08cf",
        "volume_id":"b4891f37-15b3-4a5b-90ac-98b3623fa896",
        "attached_host":"blitz7-83",
        "instance_uuid":"ad9f90d3-6040-4b97-b333-7e0a975b136c",
        "mountpoint":"\/dev\/vda",
        "attach_time":"2015-02-11 16:52:21",
        "detach_time":"2017-03-15 14:55:49",
        "attach_mode":"rw",
        "attach_status":"detached"
    },
    {
        "created_at":"2015-08-20 12:14:19",
        "updated_at":"2016-01-15 19:06:09",
        "deleted_at":"2017-03-15 14:55:49",
        "deleted":"@@@_0.5",
        "id":"1b4c1faa-652d-4718-972a-733b7779c8f0",
        "volume_id":"4aa444fb-9a94-4739-bfab-a8410bc6518e",
        "attached_host":"prime-72",
        "instance_uuid":"b2c340aa-7fb6-4767-927b-6c4f6de5e07d",
        "mountpoint":"vda",
        "attach_time":"2014-12-24 11:19:04",
        "detach_time":"2017-03-15 14:55:49",
        "attach_mode":"rw",
        "attach_status":"detached"
    },
    {
        "created_at":"2015-08-20 12:14:19",
        "updated_at":"2016-01-19 16:52:19",
        "deleted_at":"2017-03-15 14:55:49",
        "deleted":1.0,
        "id":"1c5d93b2-49d0-44cf-9ead-e6fa9e858325",
        "volume_id":"bc6c5bfa-10eb-4aa4-9827-c4cd5680af94",
        "attached_host":"blitz7-83",
        "instance_uuid":"5d7b93f2-35c1-4b59-a320-c29cd1546b6b",
        "mountpoint":"\/dev\/vda",
        "attach_time":"2015-04-19 19:58:56",
        "detach_time":"2017-03-15 14:55:49",
        "attach_mode":"rw",
        "attach_status":"detached"
    },
    {
        "created_at":"2015-08-20 12:14:19",
        "updated_at":"2015-10-27 01:01:14",
        "deleted_at":"2017-03-15 14:55:49",
        "deleted":"@@@_200.0",
        "id":"1e522a45-7af2-44f6-b22c-d0a200da70c1",
        "volume_id":"f9b7b975-532f-4e2e-93a7-8733a3494e32",
        "attached_host":"blitz7-83",
        "instance_uuid":"16bcb44d-c45a-4501-9c16-77fe91cc094d",
        "mountpoint":"\/dev\/vda",
        "attach_time":"2015-04-23 20:02:56",
        "detach_time":"2017-03-15 14:55:49",
        "attach_mode":"rw",
        "attach_status":"detached"
    },
    {
        "created_at":"2015-08-20 12:14:19",
        "updated_at":"2016-01-15 15:44:53",
        "deleted_at":"2017-03-15 14:55:49",
        "deleted":"@@@_0.0",
        "id":"23412252-72e2-4ea8-bbaa-56015940c54c",
        "volume_id":"6539e2a7-70ed-4022-a23d-53aef5ac52b8",
        "attached_host":"prime-72",
        "instance_uuid":"92f3b847-4b4b-4135-95d1-39d535c421c0",
        "mountpoint":"\/dev\/vda",
        "attach_time":"2014-12-05 22:33:57",
        "detach_time":"2017-03-15 14:55:49",
        "attach_mode":"rw",
        "attach_status":"detached"
    },
    {
        "created_at":"2015-08-20 12:14:19",
        "updated_at":"2016-01-11 19:01:31",
        "deleted_at":"2017-03-15 14:55:49",
        "deleted":"@@@_-0.5",
        "id":"244a0bf2-760c-45b6-bbe9-14b7e17020f7",
        "volume_id":"f7d495df-73f1-4203-9d22-738f914ab49c",
        "attached_host":"prime-72",
        "instance_uuid":"f1b8a151-fce3-40b2-905d-29816176d0fe",
        "mountpoint":"vda",
        "attach_time":"2014-12-20 20:55:42",
        "detach_time":"2017-03-15 14:55:49",
        "attach_mode":"rw",
        "attach_status":"detached"
    },
    {
        "created_at":"2015-08-20 12:14:19",
        "updated_at":"2016-01-25 15:23:09",
        "deleted_at":"2017-03-15 14:55:49",
        "deleted":"@@@_3.0",
        "id":"24612189-6e95-4a0b-94cf-c2b91a3e6d00",
        "volume_id":"ee46e716-d1bb-484e-a166-a566e9a815d9",
        "attached_host":"prime-72",
        "instance_uuid":"8bf7fefa-a644-41b3-b060-8197f926b109",
        "mountpoint":"\/dev\/vdc",
        "attach_time":"2014-12-03 20:41:13",
        "detach_time":"2017-03-15 14:55:49",
        "attach_mode":"rw",
        "attach_status":"detached"
    },
    {
        "created_at":"2015-08-20 12:14:19",
        "updated_at":"2016-01-19 16:40:57",
        "deleted_at":"2017-03-15 14:55:49",
        "deleted":"@@@_0.99",
        "id":"24c3d06e-f15a-433b-8031-c04265b75b59",
        "volume_id":"36791a5d-bd62-4632-a939-e08a3e9eacd1",
        "attached_host":"prime-72",
        "instance_uuid":"123a359d-507a-4de3-a149-9a4cd04b04e6",
        "mountpoint":"vda",
        "attach_time":"2015-01-06 16:44:32",
        "detach_time":"2017-03-15 14:55:49",
        "attach_mode":"rw",
        "attach_status":"detached"
    },
    {
        "created_at":"2015-08-20 12:14:19",
        "updated_at":"2015-11-12 21:06:48",
        "deleted_at":"2017-03-15 14:55:49",
        "deleted":"@@@_0.0",
        "id":"25ec13b2-96ba-4260-b974-bf733cb2bdb4",
        "volume_id":"67537122-4235-46c7-ba26-4198f2d86fa7",
        "attached_host":"blitz7-83",
        "instance_uuid":"7b696b85-f089-4e55-8e84-2805fc69f534",
        "mountpoint":"\/dev\/vda",
        "attach_time":"2015-06-17 16:04:59",
        "detach_time":"2017-03-15 14:55:49",
        "attach_mode":"rw",
        "attach_status":"detached"
    },
    {
        "created_at":"2015-08-20 12:14:19",
        "updated_at":"2016-01-11 18:05:35",
        "deleted_at":"2017-03-15 14:55:49",
        "deleted":1.0,
        "id":"289a68e4-4a82-4153-8b38-342e563d893d",
        "volume_id":"daad60da-7fcd-4b0d-b843-7af3d04a68f4",
        "attached_host":"blitz7-83",
        "instance_uuid":"0ef8157e-0b50-43a6-8395-a10c79e5e2cf",
        "mountpoint":"\/dev\/vdb",
        "attach_time":"2015-04-19 18:24:30",
        "detach_time":"2017-03-15 14:55:49",
        "attach_mode":"rw",
        "attach_status":"detached"
    },
    {
        "created_at":"2015-08-20 12:14:19",
        "updated_at":"2016-01-19 19:46:50",
        "deleted_at":"2017-03-15 14:55:49",
        "deleted":"@@@_0.0",
        "id":"29cb9e7d-d8ad-4572-96aa-aa0fbb05bd88",
        "volume_id":"5c436e24-91fc-4cf6-9ee7-cc97d4d20c98",
        "attached_host":"prime-72",
        "instance_uuid":"ea4da14c-286a-4e14-ab83-ec82cf7e3aec",
        "mountpoint":"\/dev\/vda",
        "attach_time":"2015-04-14 13:10:57",
        "detach_time":"2017-03-15 14:55:49",
        "attach_mode":"rw",
        "attach_status":"detached"
    },
    {
        "created_at":"2015-08-20 12:14:19",
        "updated_at":"2016-01-21 21:53:29",
        "deleted_at":"2017-03-15 14:55:49",
        "deleted":"@@@_0.01",
        "id":"2a2b1ac8-a008-4fe3-9cc8-37980243b7be",
        "volume_id":"6c5e09c2-2fc9-4bc7-83c0-9a039e06f501",
        "attached_host":"prime-72",
        "instance_uuid":"5a3bf95a-f84b-4256-94a0-23df43b31dab",
        "mountpoint":"vda",
        "attach_time":"2014-12-05 18:20:34",
        "detach_time":"2017-03-15 14:55:49",
        "attach_mode":"rw",
        "attach_status":"detached"
    },
    {
        "created_at":"2015-08-20 12:14:19",
        "updated_at":"2015-12-29 17:34:08",
        "deleted_at":"2017-03-15 14:55:49",
        "deleted":1.0,
        "id":"2c46989d-387c-4f4a-b7f8-315b3b25d12d",
        "volume_id":"8b413aa7-e7c1-4b86-ae47-9d80c8045f7a",
        "attached_host":"prime-72",
        "instance_uuid":"c1cd4128-7362-44ef-ba62-ed2a9788c238",
        "mountpoint":"vda",
        "attach_time":"2014-12-11 21:48:12",
        "detach_time":"2017-03-15 14:55:49",
        "attach_mode":"rw",
        "attach_status":"detached"
    },
    {
        "created_at":"2015-08-20 12:14:19",
        "updated_at":"2016-11-15 03:37:38",
        "deleted_at":"2017-03-15 14:55:49",
        "deleted":"@@@_0.001",
        "id":"2d0694a0-5abb-4bda-82f2-a756db41b6a1",
        "volume_id":"f01c645d-eee1-48e4-8e53-b6f10dd49d46",
        "attached_host":"blitz7-83",
        "instance_uuid":"1cf52ca5-4012-43ab-a134-756e7a83c966",
        "mountpoint":"\/dev\/vda",
        "attach_time":"2015-06-30 19:12:19",
        "detach_time":"2017-03-15 14:55:49",
        "attach_mode":"rw",
        "attach_status":"detached"
    },
    {
        "created_at":"2015-08-20 12:14:19",
        "updated_at":"2015-09-09 14:03:44",
        "deleted_at":"2017-03-15 14:55:49",
        "deleted":"@@@_0.0",
        "id":"2d0e5229-c147-4380-a5c2-91d0f756f53e",
        "volume_id":"7d3b5ad0-388c-4893-ae3c-79723ecc04dd",
        "attached_host":"blitz7-83",
        "instance_uuid":"5ac1767a-9d1b-4fab-8214-db0556c3e584",
        "mountpoint":"\/dev\/vda",
        "attach_time":"2015-06-03 17:59:07",
        "detach_time":"2017-03-15 14:55:49",
        "attach_mode":"rw",
        "attach_status":"detached"
    },
    {
        "created_at":"2015-08-20 12:14:19",
        "updated_at":"2016-01-22 16:01:24",
        "deleted_at":"2017-03-15 14:55:49",
        "deleted":"@@@_-0.01",
        "id":"303f3812-605d-491e-984a-3f06199f762b",
        "volume_id":"784d3572-b1d6-425e-b1c0-58d1b2c21ed0",
        "attached_host":"prime-72",
        "instance_uuid":"922e5245-cbca-4ad8-bffa-f2cfbce5a4e3",
        "mountpoint":"vda",
        "attach_time":"2014-12-01 23:35:04",
        "detach_time":"2017-03-15 14:55:49",
        "attach_mode":"rw",
        "attach_status":"detached"
    },
    {
        "created_at":"2015-08-20 12:14:19",
        "updated_at":"2015-12-14 20:22:37",
        "deleted_at":"2017-03-15 14:55:49",
        "deleted":1.0,
        "id":"338b1127-59a6-4faf-9773-b41d4ca19730",
        "volume_id":"b876c27e-7461-4eee-84ab-57ff41070ba0",
        "attached_host":"prime-72",
        "instance_uuid":"2ec1cf69-b6cd-481d-bccb-ab708a029ba5",
        "mountpoint":"vda",
        "attach_time":"2014-12-30 21:47:50",
        "detach_time":"2017-03-15 14:55:49",
        "attach_mode":"rw",
        "attach_status":"detached"
    },
    {
        "created_at":"2015-08-20 12:14:19",
        "updated_at":"2016-01-22 15:30:43",
        "deleted_at":"2017-03-15 14:55:49",
        "deleted":"@@@_-5.0",
        "id":"34d2b5f0-3183-44ae-975c-10b25e086982",
        "volume_id":"f7698aea-036c-4a58-bd08-710b555c0b90",
        "attached_host":"prime-72",
        "instance_uuid":"c70b29ab-d4a2-43ea-bdea-1496c288139f",
        "mountpoint":"vda",
        "attach_time":"2014-03-29 21:49:59",
        "detach_time":"2017-03-15 14:55:49",
        "attach_mode":"rw",
        "attach_status":"detached"
    },
    {
        "created_at":"2015-08-20 12:14:19",
        "updated_at":"2016-01-15 15:44:50",
        "deleted_at":"2017-03-15 14:55:49",
        "deleted":"@@@_0.0",
        "id":"35111667-940e-4402-934b-37c3e6e5153d",
        "volume_id":"88c4cf59-066e-41e3-8ddc-fe68bc4f42e7",
        "attached_host":"prime-72",
        "instance_uuid":"d33b3743-4ca0-429c-92c1-7160b5c3db9e",
        "mountpoint":"\/dev\/vda",
        "attach_time":"2014-12-05 22:44:21",
        "detach_time":"2017-03-15 14:55:49",
        "attach_mode":"rw",
        "attach_status":"detached"
    },
    {
        "created_at":"2015-08-20 12:14:19",
        "updated_at":"2016-01-21 16:50:34",
        "deleted_at":"2017-03-15 14:55:49",
        "deleted":"@@@_2.0",
        "id":"3695c331-6b45-4d0f-9ac0-63352ecd7eed",
        "volume_id":"a13833a2-eb33-4624-9bd1-af1812d7ca25",
        "attached_host":"prime-72",
        "instance_uuid":"b941024f-81a0-4aca-81e6-fd73f0dd6e51",
        "mountpoint":"vda",
        "attach_time":"2014-12-05 16:50:44",
        "detach_time":"2017-03-15 14:55:49",
        "attach_mode":"rw",
        "attach_status":"detached"
    },
    {
        "created_at":"2015-08-20 12:14:19",
        "updated_at":"2016-01-20 21:36:32",
        "deleted_at":"2017-03-15 14:55:49",
        "deleted":"@@@_1.5",
        "id":"39b344d7-17d8-4679-a3ca-027dbab87537",
        "volume_id":"30f52d3c-2755-4db8-9737-c6094963f2c6",
        "attached_host":"prime-72",
        "instance_uuid":"5f9510f5-3635-47dc-8b24-5cf786ca79e7",
        "mountpoint":"vda",
        "attach_time":"2014-10-25 00:50:00",
        "detach_time":"2017-03-15 14:55:49",
        "attach_mode":"rw",
        "attach_status":"detached"
    },
    {
        "created_at":"2015-08-20 12:14:19",
        "updated_at":"2016-04-25 22:33:52",
        "deleted_at":"2017-03-15 14:55:49",
        "deleted":"@@@_-1.0",
        "id":"3f6d05ef-f3d4-402c-985d-47c4779057e8",
        "volume_id":"0e35db85-dc9f-457b-834e-bf1497cfdb56",
        "attached_host":"blitz7-83",
        "instance_uuid":"36dbaa49-aa5c-4f11-81cf-36d5acbe6f3c",
        "mountpoint":"\/dev\/vda",
        "attach_time":"2015-06-27 17:11:40",
        "detach_time":"2017-03-15 14:55:49",
        "attach_mode":"rw",
        "attach_status":"detached"
    },
    {
        "created_at":"2015-08-20 12:14:19",
        "updated_at":"2016-01-19 15:53:24",
        "deleted_at":"2017-03-15 14:55:49",
        "deleted":"@@@_0.99",
        "id":"41410921-424b-4c52-bb22-916e05136b63",
        "volume_id":"74afed5d-1ebd-4e70-95c9-0326c8cffa15",
        "attached_host":"prime-72",
        "instance_uuid":"98ce7dab-c583-4cab-b778-096c97a7bd7e",
        "mountpoint":"vda",
        "attach_time":"2014-10-29 19:06:53",
        "detach_time":"2017-03-15 14:55:49",
        "attach_mode":"rw",
        "attach_status":"detached"
    },
    {
        "created_at":"2015-08-20 12:14:19",
        "updated_at":"2016-01-20 15:46:28",
        "deleted_at":"2017-03-15 14:55:49",
        "deleted":"@@@_1.01",
        "id":"4449ac52-90e2-4811-ae93-89210a09d71b",
        "volume_id":"61f84fb5-2079-4aad-b7b5-cf49ae1810b3",
        "attached_host":"prime-72",
        "instance_uuid":"84dc5737-81e0-4516-9c21-1c7fa8c27810",
        "mountpoint":"vda",
        "attach_time":"2014-12-05 18:14:25",
        "detach_time":"2017-03-15 14:55:49",
        "attach_mode":"rw",
        "attach_status":"detached"
    },
    {
        "created_at":"2015-08-20 12:14:19",
        "updated_at":"2016-11-15 03:36:25",
        "deleted_at":"2017-03-15 14:55:49",
        "deleted":1.0,
        "id":"45e5c47f-7f35-4eb9-a7ac-68e73d49dc42",
        "volume_id":"32341bf9-826a-49ba-98f4-c36235997b59",
        "attached_host":"blitz7-83",
        "instance_uuid":"2449eeee-2b80-40b4-b850-7c8654e33476",
        "mountpoint":"\/dev\/vda",
        "attach_time":"2015-06-30 19:13:24",
        "detach_time":"2017-03-15 14:55:49",
        "attach_mode":"rw",
        "attach_status":"detached"
    },
    {
        "created_at":"2015-08-20 12:14:19",
        "updated_at":"2015-10-23 03:50:50",
        "deleted_at":"2017-03-15 14:55:49",
        "deleted":"@@@_-0.5",
        "id":"475bb25d-f1fb-43e4-be42-07bf8b7ba955",
        "volume_id":"54973ed2-0b4e-4303-a1f7-afaae6a9267e",
        "attached_host":"prime-72",
        "instance_uuid":"2835aa6f-6100-4d54-b65e-cbf0d967c67f",
        "mountpoint":"vda",
        "attach_time":"2014-10-03 14:40:52",
        "detach_time":"2017-03-15 14:55:49",
        "attach_mode":"rw",
        "attach_status":"detached"
    },
    {
        "created_at":"2015-08-20 12:14:19",
        "updated_at":"2015-11-12 21:06:49",
        "deleted_at":"2017-03-15 14:55:49",
        "deleted":1.0,
        "id":"47a655a2-9518-43f6-93ac-7d0e6ca12563",
        "volume_id":"dd0c7ff0-65a6-4023-b1f5-803f79280a1f",
        "attached_host":"blitz7-83",
        "instance_uuid":"dea26944-4c0c-403e-985b-454703fab741",
        "mountpoint":"\/dev\/vda",
        "attach_time":"2015-06-17 16:06:11",
        "detach_time":"2017-03-15 14:55:49",
        "attach_mode":"rw",
        "attach_status":"detached"
    },
    {
        "created_at":"2015-08-20 12:14:19",
        "updated_at":"2015-09-11 11:31:02",
        "deleted_at":"2017-03-15 14:55:49",
        "deleted":"@@@_0.0",
        "id":"4ad9b6e7-d660-4bdf-896a-ebe2a92f5055",
        "volume_id":"402152fa-e932-4a2e-a007-3c5aa66e68fb",
        "attached_host":"blitz7-83",
        "instance_uuid":"bfefad8b-4b8a-4678-a1ef-dd3767f2aef9",
        "mountpoint":"\/dev\/vdb",
        "attach_time":"2015-08-11 12:25:16",
        "detach_time":"2017-03-15 14:55:49",
        "attach_mode":"rw",
        "attach_status":"detached"
    },
    {
        "created_at":"2015-08-20 12:14:19",
        "updated_at":"2016-01-19 15:53:33",
        "deleted_at":"2017-03-15 14:55:49",
        "deleted":"@@@_0.5",
        "id":"4b06fb7a-0915-4c3a-a1f2-18b601932a3b",
        "volume_id":"0693cce9-021d-4dc9-a367-53fe0b084dcd",
        "attached_host":"prime-72",
        "instance_uuid":"2b5d02f9-a561-47b6-b4c8-a2c174850a4c",
        "mountpoint":"vda",
        "attach_time":"2014-10-29 19:07:01",
        "detach_time":"2017-03-15 14:55:49",
        "attach_mode":"rw",
        "attach_status":"detached"
    },
    {
        "created_at":"2015-08-20 12:14:19",
        "updated_at":"2015-11-12 21:06:51",
        "deleted_at":"2017-03-15 14:55:49",
        "deleted":"@@@_1.1",
        "id":"4cdd6173-be38-442e-9340-a934160d2156",
        "volume_id":"e6d15d87-61f1-4a11-ba3a-9293787dcb0d",
        "attached_host":"blitz7-83",
        "instance_uuid":"d66ca437-8174-480d-ba60-7fe7c65dd6c9",
        "mountpoint":"\/dev\/vda",
        "attach_time":"2015-06-17 16:08:06",
        "detach_time":"2017-03-15 14:55:49",
        "attach_mode":"rw",
        "attach_status":"detached"
    },
    {
        "created_at":"2015-08-20 12:14:19",
        "updated_at":"2015-10-13 19:58:13",
        "deleted_at":"2017-03-15 14:55:49",
        "deleted":1.0,
        "id":"4d090b46-c297-4a05-a1bf-ff3551c80d72",
        "volume_id":"476fdab7-d927-45f9-ab7d-dd2f5fcbbe66",
        "attached_host":"flare-zenit3",
        "instance_uuid":"e9db1df5-afd0-45f6-ae73-6a812a17229c",
        "mountpoint":"vda",
        "attach_time":"2015-02-01 15:37:21",
        "detach_time":"2017-03-15 14:55:49",
        "attach_mode":"rw",
        "attach_status":"detached"
    },
    {
        "created_at":"2015-08-20 12:14:19",
        "updated_at":"2016-04-21 15:32:40",
        "deleted_at":"2017-03-15 14:55:49",
        "deleted":"@@@_0.9",
        "id":"4d2fd0be-e8e4-4908-bf6e-66b1f4516db8",
        "volume_id":"919d16c4-9631-4c89-bf62-ba8f521bff79",
        "attached_host":"blitz7-83",
        "instance_uuid":"8e91e8c8-c4d8-4419-a8ce-26f137207d26",
        "mountpoint":"\/dev\/vda",
        "attach_time":"2015-04-23 20:07:47",
        "detach_time":"2017-03-15 14:55:49",
        "attach_mode":"rw",
        "attach_status":"detached"
    },
    {
        "created_at":"2015-08-20 12:14:19",
        "updated_at":"2015-08-31 18:11:01",
        "deleted_at":"2017-03-15 14:55:49",
        "deleted":1.0,
        "id":"4d3982e8-78df-4341-ac63-7d65efb891a0",
        "volume_id":"378dff44-7260-42a0-8256-ba15a4c8bb43",
        "attached_host":"blitz7-83",
        "instance_uuid":"2b3436d7-53a9-47e9-b6f7-46ab91db28ca",
        "mountpoint":"\/dev\/vda",
        "attach_time":"2015-04-29 15:28:00",
        "detach_time":"2017-03-15 14:55:49",
        "attach_mode":"rw",
        "attach_status":"detached"
    },
    {
        "created_at":"2015-08-20 12:14:19",
        "updated_at":"2016-01-21 20:37:56",
        "deleted_at":"2017-03-15 14:55:49",
        "deleted":"@@@_2.0",
        "id":"4d5e4153-9dae-4637-a553-e0462743d6b0",
        "volume_id":"3545b7b6-d333-486b-b419-0a1cc6dd77cc",
        "attached_host":"prime-72",
        "instance_uuid":"0819b979-127c-4531-8993-f697eb71a309",
        "mountpoint":"vda",
        "attach_time":"2014-12-05 18:17:57",
        "detach_time":"2017-03-15 14:55:49",
        "attach_mode":"rw",
        "attach_status":"detached"
    },
    {
        "created_at":"2015-08-20 12:14:19",
        "updated_at":"2015-09-11 11:31:03",
        "deleted_at":"2017-03-15 14:55:49",
        "deleted":1.0,
        "id":"4fadb713-4099-4566-848e-a99def46cd02",
        "volume_id":"4a51c714-1088-40e0-a2fa-25d5591e9866",
        "attached_host":"blitz7-83",
        "instance_uuid":"d137f286-2801-4c22-8948-930a0b614295",
        "mountpoint":"\/dev\/vdb",
        "attach_time":"2015-08-11 14:38:16",
        "detach_time":"2017-03-15 14:55:49",
        "attach_mode":"rw",
        "attach_status":"detached"
    },
    {
        "created_at":"2015-08-20 12:14:19",
        "updated_at":"2016-01-14 17:44:07",
        "deleted_at":"2017-03-15 14:55:49",
        "deleted":"@@@_0.8",
        "id":"5840118f-83f6-455c-8e8c-f5c163eccddf",
        "volume_id":"534eaf7f-79b5-48d7-ac89-c347f6b5f07e",
        "attached_host":"prime-72",
        "instance_uuid":"de721328-6f2f-47ef-9b51-795f5d666700",
        "mountpoint":"\/dev\/vdb",
        "attach_time":"2014-12-05 20:39:58",
        "detach_time":"2017-03-15 14:55:49",
        "attach_mode":"rw",
        "attach_status":"detached"
    },
    {
        "created_at":"2015-08-20 12:14:19",
        "updated_at":"2015-08-27 17:10:40",
        "deleted_at":"2017-03-15 14:55:49",
        "deleted":"@@@_0.0",
        "id":"5a000c3d-08f2-4acb-8459-feb471e4f729",
        "volume_id":"a650c178-a3bd-49a4-a7b0-89b3ca11071d",
        "attached_host":"blitz7-83",
        "instance_uuid":"044e1db7-0fc4-436e-a8ac-702ad1db8c2d",
        "mountpoint":"\/dev\/vda",
        "attach_time":"2015-08-12 16:50:33",
        "detach_time":"2017-03-15 14:55:49",
        "attach_mode":"rw",
        "attach_status":"detached"
    },
    {
        "created_at":"2015-08-20 12:14:19",
        "updated_at":"2015-09-01 14:24:04",
        "deleted_at":"2017-03-15 14:55:49",
        "deleted":"@@@_1.5",
        "id":"5a70a2af-253a-4b6f-95b4-d11764dcaf8d",
        "volume_id":"c4ccd6db-f925-4768-9c89-3236219aa1d8",
        "attached_host":"blitz7-83",
        "instance_uuid":"c57c7530-89e6-4779-8efa-fd5db8d92ec6",
        "mountpoint":"\/dev\/vda",
        "attach_time":"2015-07-06 16:23:31",
        "detach_time":"2017-03-15 14:55:49",
        "attach_mode":"rw",
        "attach_status":"detached"
    },
    {
        "created_at":"2015-08-20 12:14:19",
        "updated_at":"2016-01-14 17:34:35",
        "deleted_at":"2017-03-15 14:55:49",
        "deleted":"@@@_-0.1",
        "id":"5c9d83bf-73e3-44a7-9b43-96f226940b7e",
        "volume_id":"e03e155d-5681-4c3e-98d4-b0717ec4b5f9",
        "attached_host":"prime-72",
        "instance_uuid":"453765af-6800-4190-8298-871cd0bbfc7a",
        "mountpoint":"\/dev\/vdb",
        "attach_time":"2015-03-09 23:40:10",
        "detach_time":"2017-03-15 14:55:49",
        "attach_mode":"rw",
        "attach_status":"detached"
    },
    {
        "created_at":"2015-08-20 12:14:19",
        "updated_at":"2015-12-14 20:36:10",
        "deleted_at":"2017-03-15 14:55:49",
        "deleted":"@@@_0.95",
        "id":"5cc35218-20ea-4d0e-a113-99ae2117571c",
        "volume_id":"8b7b00a7-b71a-4698-84f9-6c949b890d21",
        "attached_host":"prime-72",
        "instance_uuid":"6d3b5026-869d-4cd3-8b09-f3f0ed2f8db6",
        "mountpoint":"vda",
        "attach_time":"2014-03-30 20:35:09",
        "detach_time":"2017-03-15 14:55:49",
        "attach_mode":"rw",
        "attach_status":"detached"
    },
    {
        "created_at":"2015-08-20 12:14:19",
        "updated_at":"2016-01-11 20:57:01",
        "deleted_at":"2017-03-15 14:55:49",
        "deleted":1.0,
        "id":"5d3ae9a3-2898-4e58-b487-989be381feec",
        "volume_id":"78706d56-bc02-4750-91bb-a3807feb2a8a",
        "attached_host":"prime-72",
        "instance_uuid":"7cb0c4f2-222a-4006-b41c-547f221e883b",
        "mountpoint":"vda",
        "attach_time":"2014-09-17 11:42:32",
        "detach_time":"2017-03-15 14:55:49",
        "attach_mode":"rw",
        "attach_status":"detached"
    },
    {
        "created_at":"2015-08-20 12:14:19",
        "updated_at":"2016-01-20 21:44:57",
        "deleted_at":"2017-03-15 14:55:49",
        "deleted":"@@@_0.99",
        "id":"5e37a0a9-f805-4a2d-82be-6c708348c9b2",
        "volume_id":"e16a4d83-afc2-4a5f-ad13-31e209529058",
        "attached_host":"prime-72",
        "instance_uuid":"b9b6eb43-8ce1-49c4-be9e-3b63862af6d4",
        "mountpoint":"vda",
        "attach_time":"2014-09-16 17:07:54",
        "detach_time":"2017-03-15 14:55:49",
        "attach_mode":"rw",
        "attach_status":"detached"
    },
    {
        "created_at":"2015-08-20 12:14:19",
        "updated_at":"2016-01-19 16:19:12",
        "deleted_at":"2017-03-15 14:55:49",
        "deleted":"@@@_1.2",
        "id":"5f5a547b-84d1-4582-8120-8ad1f455e5ef",
        "volume_id":"90a4fa80-86fb-4429-8171-0bb67cfc80a6",
        "attached_host":"prime-72",
        "instance_uuid":"973defde-8301-45ad-8c60-45d3578594b8",
        "mountpoint":"vda",
        "attach_time":"2014-10-31 14:04:39",
        "detach_time":"2017-03-15 14:55:49",
        "attach_mode":"rw",
        "attach_status":"detached"
    },
    {
        "created_at":"2015-08-20 12:14:19",
        "updated_at":"2015-12-29 20:07:45",
        "deleted_at":"2017-03-15 14:55:49",
        "deleted":1.0,
        "id":"62361e07-8758-4cb6-80a1-9ec14c5c97e0",
        "volume_id":"fb388f70-ad44-4941-ac6b-d58513d767a5",
        "attached_host":"prime-72",
        "instance_uuid":"96a56a7c-f625-4854-86c6-4b362a3d9cd7",
        "mountpoint":"\/dev\/vdc",
        "attach_time":"2014-12-04 05:01:02",
        "detach_time":"2017-03-15 14:55:49",
        "attach_mode":"rw",
        "attach_status":"detached"
    },
    {
        "created_at":"2015-08-20 12:14:19",
        "updated_at":"2016-03-01 23:08:03",
        "deleted_at":"2017-03-15 14:55:49",
        "deleted":"@@@_0.0",
        "id":"62e775ea-09a1-4cda-af92-880c68c8ab47",
        "volume_id":"12411d4c-8e4c-4f36-9374-f2415ffb2d8b",
        "attached_host":"blitz7-83",
        "instance_uuid":"012db731-d632-483a-8399-f6a2bd2493e2",
        "mountpoint":"\/dev\/vda",
        "attach_time":"2015-07-23 02:15:17",
        "detach_time":"2017-03-15 14:55:49",
        "attach_mode":"rw",
        "attach_status":"detached"
    },
    {
        "created_at":"2015-08-20 12:14:19",
        "updated_at":"2015-10-15 09:10:41",
        "deleted_at":"2017-03-15 14:55:49",
        "deleted":1.0,
        "id":"6a77c4bd-177a-4668-adc8-eede37af996b",
        "volume_id":"f60fcf5a-203e-4737-8c2c-5d13f4a996cf",
        "attached_host":"blitz7-83",
        "instance_uuid":"e155cd94-d0c6-4039-8ae4-006ab520e1fd",
        "mountpoint":"\/dev\/vda",
        "attach_time":"2015-02-11 17:32:12",
        "detach_time":"2017-03-15 14:55:49",
        "attach_mode":"rw",
        "attach_status":"detached"
    },
    {
        "created_at":"2015-08-20 12:14:19",
        "updated_at":"2016-01-21 20:03:22",
        "deleted_at":"2017-03-15 14:55:49",
        "deleted":"@@@_1.3",
        "id":"6bdab9d9-3695-4d91-838e-9183df026138",
        "volume_id":"1d709a46-aede-4632-8954-8c41ea0fe4cc",
        "attached_host":"prime-72",
        "instance_uuid":"89c0b27c-c177-47e0-bfc2-afef1d2ab875",
        "mountpoint":"vda",
        "attach_time":"2014-12-05 16:44:49",
        "detach_time":"2017-03-15 14:55:49",
        "attach_mode":"rw",
        "attach_status":"detached"
    },
    {
        "created_at":"2015-08-20 12:14:19",
        "updated_at":"2016-01-12 21:01:13",
        "deleted_at":"2017-03-15 14:55:49",
        "deleted":1.0,
        "id":"754247f7-545b-43d6-aa03-b8660e1fe6ee",
        "volume_id":"464951c9-809f-47c0-a4ec-637aa9959777",
        "attached_host":"prime-72",
        "instance_uuid":"7f5b6bcb-247e-4b31-8e6c-135edb2aaa0d",
        "mountpoint":"vda",
        "attach_time":"2015-01-12 15:47:13",
        "detach_time":"2017-03-15 14:55:49",
        "attach_mode":"rw",
        "attach_status":"detached"
    },
    {
        "created_at":"2015-08-20 12:14:19",
        "updated_at":"2015-11-13 00:44:00",
        "deleted_at":"2017-03-15 14:55:49",
        "deleted":"@@@_0.0",
        "id":"7d5d9f4c-ba5f-4385-9e2e-7f5a7b7d3468",
        "volume_id":"3607c480-e649-40cd-b595-5d83c17351d1",
        "attached_host":"blitz7-83",
        "instance_uuid":"9015054f-db30-415c-a2f5-936467325e65",
        "mountpoint":"\/dev\/vda",
        "attach_time":"2015-07-30 21:54:45",
        "detach_time":"2017-03-15 14:55:49",
        "attach_mode":"rw",
        "attach_status":"detached"
    },
    {
        "created_at":"2015-08-20 12:14:19",
        "updated_at":"2015-11-23 15:20:56",
        "deleted_at":"2017-03-15 14:55:49",
        "deleted":"@@@_2.0",
        "id":"7ddad7a6-6cec-4347-86e8-d0798afa6141",
        "volume_id":"76ad2b4e-6154-411a-990c-c7fc0789e31c",
        "attached_host":"blitz7-83",
        "instance_uuid":"e6ec18ed-8828-4592-b00c-81444a341e96",
        "mountpoint":"\/dev\/vdb",
        "attach_time":"2015-06-14 21:07:04",
        "detach_time":"2017-03-15 14:55:49",
        "attach_mode":"rw",
        "attach_status":"detached"
    },
    {
        "created_at":"2015-08-20 12:14:19",
        "updated_at":"2015-09-11 11:31:03",
        "deleted_at":"2017-03-15 14:55:49",
        "deleted":"@@@_-1.0",
        "id":"7ed20a17-85a4-4feb-b70f-fc4514cccb8d",
        "volume_id":"45cc9cd7-fffb-4ef1-adb6-704d8143b0c1",
        "attached_host":"blitz7-83",
        "instance_uuid":"1f517f8b-0dff-4c70-8991-456babbe299e",
        "mountpoint":"\/dev\/vdb",
        "attach_time":"2015-08-11 12:26:00",
        "detach_time":"2017-03-15 14:55:49",
        "attach_mode":"rw",
        "attach_status":"detached"
    },
    {
        "created_at":"2015-08-20 12:14:19",
        "updated_at":"2015-08-26 11:31:07",
        "deleted_at":"2017-03-15 14:55:49",
        "deleted":"@@@_100.0",
        "id":"7ed96c96-b450-4551-90c0-169b5b05b885",
        "volume_id":"8e69b575-ffc8-45e6-8d88-4dabe0fd9754",
        "attached_host":"blitz7-83",
        "instance_uuid":"bf51e028-a4bb-4b3d-a3d8-c4db6eda074a",
        "mountpoint":"\/dev\/vda",
        "attach_time":"2015-08-20 12:45:54",
        "detach_time":"2017-03-15 14:55:49",
        "attach_mode":"rw",
        "attach_status":"detached"
    },
    {
        "created_at":"2015-08-20 12:14:19",
        "updated_at":"2015-12-15 17:19:51",
        "deleted_at":"2017-03-15 14:55:49",
        "deleted":"@@@_0.5",
        "id":"7fae13d7-7a0f-4135-bbc5-ec13e3a6c6b1",
        "volume_id":"ae459319-62c5-4b20-a3a2-e7cba096c47b",
        "attached_host":"prime-72",
        "instance_uuid":"c92cabf7-0929-4af8-8608-b5326588a4f0",
        "mountpoint":"\/dev\/vda",
        "attach_time":"2015-02-27 17:24:55",
        "detach_time":"2017-03-15 14:55:49",
        "attach_mode":"rw",
        "attach_status":"detached"
    },
    {
        "created_at":"2015-08-20 12:14:19",
        "updated_at":"2016-01-15 21:49:06",
        "deleted_at":"2017-03-15 14:55:49",
        "deleted":"@@@_10.0",
        "id":"81b02ea6-56b5-4ba5-b081-18929e167487",
        "volume_id":"af58e07d-2b41-42ea-bcd0-d869be51e94c",
        "attached_host":"prime-72",
        "instance_uuid":"63675066-2c7b-4428-818b-719e745e2811",
        "mountpoint":"vda",
        "attach_time":"2015-01-14 21:22:47",
        "detach_time":"2017-03-15 14:55:49",
        "attach_mode":"rw",
        "attach_status":"detached"
    },
    {
        "created_at":"2015-08-20 12:14:19",
        "updated_at":"2015-12-27 17:05:07",
        "deleted_at":"2017-03-15 14:55:49",
        "deleted":"@@@_0.0",
        "id":"82573dce-af05-4ac0-adfc-1a756cc4fa13",
        "volume_id":"49315c2a-e3d0-4327-b34b-1afc30dbbba0",
        "attached_host":"prime-72",
        "instance_uuid":"f2c49f38-69b2-455a-9449-0bb800c83264",
        "mountpoint":"\/dev\/vda",
        "attach_time":"2015-05-27 19:06:02",
        "detach_time":"2017-03-15 14:55:49",
        "attach_mode":"rw",
        "attach_status":"detached"
    },
    {
        "created_at":"2015-08-20 12:14:19",
        "updated_at":"2015-10-15 09:11:28",
        "deleted_at":"2017-03-15 14:55:49",
        "deleted":"@@@_1.5",
        "id":"83176a96-393b-4677-a4fa-210ec9f23da6",
        "volume_id":"9abb2a21-a65c-4c5a-aaa0-861eb910fa83",
        "attached_host":"blitz7-83",
        "instance_uuid":"ad9f90d3-6040-4b97-b333-7e0a975b136c",
        "mountpoint":"\/dev\/vdc",
        "attach_time":"2015-02-11 17:01:55",
        "detach_time":"2017-03-15 14:55:49",
        "attach_mode":"rw",
        "attach_status":"detached"
    },
    {
        "created_at":"2015-08-20 12:14:19",
        "updated_at":"2015-11-30 18:20:55",
        "deleted_at":"2017-03-15 14:55:49",
        "deleted":"@@@_-0.5",
        "id":"83e82a14-db25-4f1e-88e6-05c240c42a29",
        "volume_id":"f5c1a1fd-ad79-471a-863d-0ea45700bf72",
        "attached_host":"prime-72",
        "instance_uuid":"1726b5ac-f97e-4a58-a724-d7509f749604",
        "mountpoint":"vda",
        "attach_time":"2014-12-11 19:07:10",
        "detach_time":"2017-03-15 14:55:49",
        "attach_mode":"rw",
        "attach_status":"detached"
    },
    {
        "created_at":"2015-08-20 12:14:19",
        "updated_at":"2017-02-12 18:45:52",
        "deleted_at":"2017-03-15 14:55:49",
        "deleted":"@@@_999.0",
        "id":"8bdb3f4c-3f09-4d51-b3e0-d13dd6ae8b76",
        "volume_id":"47062c04-319e-4cdf-938d-bb6c15a91355",
        "attached_host":"blitz7-83",
        "instance_uuid":"e7bfb0af-2c87-4f05-8b1a-7c4b1c9cd03d",
        "mountpoint":"\/dev\/vda",
        "attach_time":"2015-03-25 04:34:46",
        "detach_time":"2017-03-15 14:55:49",
        "attach_mode":"rw",
        "attach_status":"detached"
    },
    {
        "created_at":"2015-08-20 12:14:19",
        "updated_at":"2016-01-15 19:05:37",
        "deleted_at":"2017-03-15 14:55:49",
        "deleted":"@@@_-10.0",
        "id":"8db45a56-1b19-46f3-850f-0a969647dadb",
        "volume_id":"9eb2719f-bdb8-4f6e-a079-4ef57ee3cc94",
        "attached_host":"prime-72",
        "instance_uuid":"9c70a51c-ac6f-463b-8c48-0ef7e16c8af6",
        "mountpoint":"\/dev\/vda",
        "attach_time":"2015-04-08 16:30:47",
        "detach_time":"2017-03-15 14:55:49",
        "attach_mode":"rw",
        "attach_status":"detached"
    },
    {
        "created_at":"2015-08-20 12:14:19",
        "updated_at":"2015-11-12 21:06:52",
        "deleted_at":"2017-03-15 14:55:49",
        "deleted":"@@@_3.14",
        "id":"8ff13e01-8914-49ff-9ec8-8740c7d4a3bd",
        "volume_id":"8fd91d31-20bd-4ffa-b738-1b8aef381db1",
        "attached_host":"blitz7-83",
        "instance_uuid":"4c6fecfe-30f2-4413-855e-0e65e4099a01",
        "mountpoint":"\/dev\/vda",
        "attach_time":"2015-06-09 20:06:42",
        "detach_time":"2017-03-15 14:55:49",
        "attach_mode":"rw",
        "attach_status":"detached"
    },
    {
        "created_at":"2015-08-20 12:14:19",
        "updated_at":"2016-01-19 15:53:30",
        "deleted_at":"2017-03-15 14:55:49",
        "deleted":1.0,
        "id":"903e3989-8e25-4de3-b7b8-b998d479c7a5",
        "volume_id":"c60a749f-ad90-495f-8dcb-2f7c3be80643",
        "attached_host":"prime-72",
        "instance_uuid":"02907b0a-2db3-41cf-87f8-265934865f79",
        "mountpoint":"vda",
        "attach_time":"2014-10-29 19:06:50",
        "detach_time":"2017-03-15 14:55:49",
        "attach_mode":"rw",
        "attach_status":"detached"
    },
    {
        "created_at":"2015-08-20 12:14:19",
        "updated_at":"2016-01-24 23:19:18",
        "deleted_at":"2017-03-15 14:55:49",
        "deleted":1.0,
        "id":"9125628f-fb9a-4469-a36f-e0a48283cf4a",
        "volume_id":"8311edf1-6e76-4f04-90d0-c3f3bc38a0b5",
        "attached_host":"prime-72",
        "instance_uuid":"470cc19e-13d2-4682-b0a6-59614cbdc4d0",
        "mountpoint":"vda",
        "attach_time":"2014-11-18 13:28:38",
        "detach_time":"2017-03-15 14:55:49",
        "attach_mode":"rw",
        "attach_status":"detached"
    },
    {
        "created_at":"2015-08-20 12:14:19",
        "updated_at":"2016-05-23 17:02:58",
        "deleted_at":"2017-03-15 14:55:49",
        "deleted":1.0,
        "id":"923633a9-a265-4c21-ac4b-c1cb44ad0015",
        "volume_id":"a3f4f56d-f5a3-495b-b906-b5e6c92c4ca1",
        "attached_host":"blitz7-83",
        "instance_uuid":"334816d9-0f29-418f-b86c-83762caf1b1a",
        "mountpoint":"\/dev\/vdb",
        "attach_time":"2015-05-18 13:03:29",
        "detach_time":"2017-03-15 14:55:49",
        "attach_mode":"rw",
        "attach_status":"detached"
    },
    {
        "created_at":"2015-08-20 12:14:19",
        "updated_at":"2016-01-20 16:13:49",
        "deleted_at":"2017-03-15 14:55:49",
        "deleted":1.0,
        "id":"931789a7-eb8f-44ed-90f2-e46209be2e9a",
        "volume_id":"3239178c-d30c-4c86-bad9-3d1ffc7c9d42",
        "attached_host":"prime-72",
        "instance_uuid":"8b12fab9-7c7a-43c9-b26b-3732e91f710a",
        "mountpoint":"vda",
        "attach_time":"2014-12-05 18:25:15",
        "detach_time":"2017-03-15 14:55:49",
        "attach_mode":"rw",
        "attach_status":"detached"
    },
    {
        "created_at":"2015-08-20 12:14:19",
        "updated_at":"2016-01-21 19:51:31",
        "deleted_at":"2017-03-15 14:55:49",
        "deleted":1.0,
        "id":"95c28c6f-5f8a-42b7-a0b8-9069e5dbb5ab",
        "volume_id":"70920592-6226-4262-976c-1f8ce7b043da",
        "attached_host":"prime-72",
        "instance_uuid":"d7465b0a-a40e-48e1-9a3e-91d434ed2e81",
        "mountpoint":"vda",
        "attach_time":"2014-12-05 18:15:57",
        "detach_time":"2017-03-15 14:55:49",
        "attach_mode":"rw",
        "attach_status":"detached"
    },
    {
        "created_at":"2015-08-20 12:14:19",
        "updated_at":"2016-02-08 15:35:14",
        "deleted_at":"2017-03-15 14:55:49",
        "deleted":1.0,
        "id":"95d0f967-5bc5-4c0c-9555-2dca07b67d7d",
        "volume_id":"0af016b1-f382-49f7-825d-eab67147880b",
        "attached_host":"blitz7-83",
        "instance_uuid":"9fc89cf3-85ea-477e-b6d8-cb55545df10f",
        "mountpoint":"\/dev\/vda",
        "attach_time":"2015-06-05 20:32:39",
        "detach_time":"2017-03-15 14:55:49",
        "attach_mode":"rw",
        "attach_status":"detached"
    },
    {
        "created_at":"2015-08-20 12:14:19",
        "updated_at":"2015-10-29 14:46:21",
        "deleted_at":"2017-03-15 14:55:49",
        "deleted":1.0,
        "id":"963cead0-74a1-4e4d-bab7-219745b574fd",
        "volume_id":"b9e401c3-1b9e-4212-b0c6-34ecc2d21780",
        "attached_host":"prime-72",
        "instance_uuid":"0c74df25-69c3-4c45-9ef0-7698b0d6f3ba",
        "mountpoint":"vda",
        "attach_time":"2014-12-10 19:49:12",
        "detach_time":"2017-03-15 14:55:49",
        "attach_mode":"rw",
        "attach_status":"detached"
    },
    {
        "created_at":"2015-08-20 12:14:19",
        "updated_at":"2016-01-15 15:44:55",
        "deleted_at":"2017-03-15 14:55:49",
        "deleted":1.0,
        "id":"989a8a74-a78a-40c6-b035-c57584336329",
        "volume_id":"dacbc39d-c13a-448e-bde0-5b608451abfc",
        "attached_host":"prime-72",
        "instance_uuid":"92f3b847-4b4b-4135-95d1-39d535c421c0",
        "mountpoint":"\/dev\/vdb",
        "attach_time":"2014-12-05 22:34:00",
        "detach_time":"2017-03-15 14:55:49",
        "attach_mode":"rw",
        "attach_status":"detached"
    },
    {
        "created_at":"2015-08-20 12:14:19",
        "updated_at":"2016-10-26 16:32:05",
        "deleted_at":"2017-03-15 14:55:49",
        "deleted":1.0,
        "id":"9954a10a-ab94-412f-bfb6-7f5138214bc3",
        "volume_id":"935d5ca7-1f14-4441-96a3-d1bf8c6f6a04",
        "attached_host":"flare-zenit3",
        "instance_uuid":"e5ad9683-7de9-425d-88b8-9bf979339dc8",
        "mountpoint":"\/dev\/vda",
        "attach_time":"2015-03-12 00:53:57",
        "detach_time":"2017-03-15 14:55:49",
        "attach_mode":"rw",
        "attach_status":"detached"
    },
    {
        "created_at":"2015-08-20 12:14:19",
        "updated_at":"2016-01-12 20:39:44",
        "deleted_at":"2017-03-15 14:55:49",
        "deleted":1.0,
        "id":"9ac43800-b0a7-472e-bb5d-12877d1b6d70",
        "volume_id":"f5467e1a-e810-40e5-b36e-06d43be1ce54",
        "attached_host":"prime-72",
        "instance_uuid":"5462b645-90e7-429d-a173-a01cd9cc2154",
        "mountpoint":"vda",
        "attach_time":"2014-12-05 18:24:10",
        "detach_time":"2017-03-15 14:55:49",
        "attach_mode":"rw",
        "attach_status":"detached"
    },
    {
        "created_at":"2015-08-20 12:14:19",
        "updated_at":"2016-01-05 21:22:49",
        "deleted_at":"2017-03-15 14:55:49",
        "deleted":1.0,
        "id":"9e993fae-e852-4f85-ab1f-a5f9d36fa04c",
        "volume_id":"d139f6f0-9908-48b3-a0cd-d807a8087091",
        "attached_host":"prime-72",
        "instance_uuid":"8f038751-257e-4eea-9391-bba7b2ae9099",
        "mountpoint":"\/dev\/vda",
        "attach_time":"2015-04-13 15:48:39",
        "detach_time":"2017-03-15 14:55:49",
        "attach_mode":"rw",
        "attach_status":"detached"
    },
    {
        "created_at":"2015-08-20 12:14:19",
        "updated_at":"2016-12-08 15:38:54",
        "deleted_at":"2017-03-15 14:55:49",
        "deleted":1.0,
        "id":"a1eb043b-16e5-457c-b3ad-1fd9c8a8a7b0",
        "volume_id":"16546dc3-92c8-48f0-9894-628607400ec9",
        "attached_host":"blitz7-83",
        "instance_uuid":"4ef1868c-5440-4799-8743-8d719e5f2d80",
        "mountpoint":"\/dev\/vdb",
        "attach_time":"2015-02-25 05:45:10",
        "detach_time":"2017-03-15 14:55:49",
        "attach_mode":"rw",
        "attach_status":"detached"
    },
    {
        "created_at":"2015-08-20 12:14:19",
        "updated_at":"2016-03-31 17:39:06",
        "deleted_at":"2017-03-15 14:55:49",
        "deleted":1.0,
        "id":"a615a539-858b-4e5b-956c-9ec6bd6ebf4d",
        "volume_id":"c4805dfe-db3e-4d5c-86c8-dcc5c00fe4eb",
        "attached_host":"blitz7-83",
        "instance_uuid":"e3a044a4-ef87-4e26-9874-264e4f3dd19d",
        "mountpoint":"\/dev\/vda",
        "attach_time":"2015-07-14 01:34:27",
        "detach_time":"2017-03-15 14:55:49",
        "attach_mode":"rw",
        "attach_status":"detached"
    },
    {
        "created_at":"2015-08-20 12:14:19",
        "updated_at":"2015-09-11 20:36:27",
        "deleted_at":"2017-03-15 14:55:49",
        "deleted":1.0,
        "id":"a829c116-ab28-45cb-8991-f6573b5c5bbb",
        "volume_id":"6b8f4be8-8e99-4d1b-b4a6-53fc47198258",
        "attached_host":"flare-zenit3",
        "instance_uuid":"d1e85db4-5aa4-4510-902f-285704ffc8ef",
        "mountpoint":"\/dev\/vdb",
        "attach_time":"2015-04-13 15:13:17",
        "detach_time":"2017-03-15 14:55:49",
        "attach_mode":"rw",
        "attach_status":"detached"
    },
    {
        "created_at":"2015-08-20 12:14:19",
        "updated_at":"2016-01-25 15:21:24",
        "deleted_at":"2017-03-15 14:55:49",
        "deleted":1.0,
        "id":"a9ce91b9-29b5-44ed-b0cd-210cfb0ba116",
        "volume_id":"6a1fca0f-ef86-41b6-82cd-c84ce4a935aa",
        "attached_host":"prime-72",
        "instance_uuid":"1fa1b103-b7b8-46a5-b479-8a455f605410",
        "mountpoint":"vda",
        "attach_time":"2014-09-20 04:25:42",
        "detach_time":"2017-03-15 14:55:49",
        "attach_mode":"rw",
        "attach_status":"detached"
    },
    {
        "created_at":"2015-08-20 12:14:19",
        "updated_at":"2015-10-23 03:50:48",
        "deleted_at":"2017-03-15 14:55:49",
        "deleted":1.0,
        "id":"a9efafae-b5c8-47b9-b96d-de25d2335af4",
        "volume_id":"726c0b9f-0445-44b4-9100-97b3b9237ec2",
        "attached_host":"blitz7-83",
        "instance_uuid":"bbb0452b-efbb-43ab-b0eb-46c1068fca6b",
        "mountpoint":"\/dev\/vda",
        "attach_time":"2015-08-05 14:21:41",
        "detach_time":"2017-03-15 14:55:49",
        "attach_mode":"rw",
        "attach_status":"detached"
    },
    {
        "created_at":"2015-08-20 12:14:19",
        "updated_at":"2015-08-23 09:33:02",
        "deleted_at":"2017-03-15 14:55:49",
        "deleted":1.0,
        "id":"aac3b1c6-752d-4c78-8200-9c8ea82c9ac9",
        "volume_id":"bfc27d51-b79e-4772-aa96-6db3db5c8b5e",
        "attached_host":"blitz7-83",
        "instance_uuid":"92531940-d73e-46b8-8e74-ada2e1913957",
        "mountpoint":"\/dev\/vda",
        "attach_time":"2015-07-12 22:54:29",
        "detach_time":"2017-03-15 14:55:49",
        "attach_mode":"rw",
        "attach_status":"detached"
    },
    {
        "created_at":"2015-08-20 12:14:19",
        "updated_at":"2015-09-11 11:31:03",
        "deleted_at":"2017-03-15 14:55:49",
        "deleted":1.0,
        "id":"ac56d960-9107-48a4-96a5-f162b0d34db1",
        "volume_id":"be0c8c0b-d9e8-472e-9cce-453fea9cf6e9",
        "attached_host":"blitz7-83",
        "instance_uuid":"be73ae4a-7759-4178-9710-f09bbc3af914",
        "mountpoint":"\/dev\/vdb",
        "attach_time":"2015-08-11 12:27:23",
        "detach_time":"2017-03-15 14:55:49",
        "attach_mode":"rw",
        "attach_status":"detached"
    },
    {
        "created_at":"2015-08-20 12:14:19",
        "updated_at":"2016-01-13 15:26:53",
        "deleted_at":"2017-03-15 14:55:49",
        "deleted":"@@@_2",
        "id":"acdf0e3c-e340-4c7a-9538-c0f66abd0086",
        "volume_id":"89398b20-b9d7-4268-93d1-a8daf40c901c",
        "attached_host":"prime-72",
        "instance_uuid":"aaf0ed28-af06-441e-a8b5-81822bbf045c",
        "mountpoint":"vda",
        "attach_time":"2014-12-05 18:21:28",
        "detach_time":"2017-03-15 14:55:49",
        "attach_mode":"rw",
        "attach_status":"detached"
    },
    {
        "created_at":"2015-08-20 12:14:19",
        "updated_at":"2015-12-02 22:34:51",
        "deleted_at":"2017-03-15 14:55:49",
        "deleted":"@@@_0",
        "id":"afa34dc7-18ba-4a41-82a0-367d30f34767",
        "volume_id":"3073ed7c-7ca2-4260-bb00-d20775ad17fa",
        "attached_host":"prime-72",
        "instance_uuid":"d81c8c7f-8e3c-4493-9263-adfe33d5383b",
        "mountpoint":"\/dev\/vda",
        "attach_time":"2015-05-15 18:38:28",
        "detach_time":"2017-03-15 14:55:49",
        "attach_mode":"rw",
        "attach_status":"detached"
    },
    {
        "created_at":"2015-08-20 12:14:19",
        "updated_at":"2016-06-15 11:52:09",
        "deleted_at":"2017-03-15 14:55:49",
        "deleted":1,
        "id":"b0bc6402-0007-49b5-8c22-de53541fd4bd",
        "volume_id":"f72e8ba7-69ed-40e1-be35-e6f36ffe66f0",
        "attached_host":"blitz7-83",
        "instance_uuid":"fdd31b0e-ca57-4e96-aa6c-0018a5237bb7",
        "mountpoint":"\/dev\/vda",
        "attach_time":"2015-07-20 17:59:55",
        "detach_time":"2017-03-15 14:55:49",
        "attach_mode":"rw",
        "attach_status":"detached"
    },
    {
        "created_at":"2015-08-20 12:14:19",
        "updated_at":"2015-09-01 14:24:04",
        "deleted_at":"2017-03-15 14:55:49",
        "deleted":1,
        "id":"b3e6b716-c027-4e5a-93a8-5462121fe5ad",
        "volume_id":"00cd1be1-c539-4165-bc55-85123eed1bc7",
        "attached_host":"blitz7-83",
        "instance_uuid":"f004dd93-5baf-44bf-94fc-2c220cc4b0a9",
        "mountpoint":"\/dev\/vda",
        "attach_time":"2015-07-06 16:25:13",
        "detach_time":"2017-03-15 14:55:49",
        "attach_mode":"rw",
        "attach_status":"detached"
    },
    {
        "created_at":"2015-08-20 12:14:19",
        "updated_at":"2016-01-19 15:53:30",
        "deleted_at":"2017-03-15 14:55:49",
        "deleted":"@@@_0",
        "id":"b6026368-cefe-4a56-b29c-5a1958ad36f2",
        "volume_id":"f2f23485-b232-4a77-b41d-9c6a10d19867",
        "attached_host":"prime-72",
        "instance_uuid":"1d69eba0-d154-4733-9ce8-060ad383ef7a",
        "mountpoint":"vda",
        "attach_time":"2014-10-29 19:06:50",
        "detach_time":"2017-03-15 14:55:49",
        "attach_mode":"rw",
        "attach_status":"detached"
    },
    {
        "created_at":"2015-08-20 12:14:19",
        "updated_at":"2016-01-19 15:53:31",
        "deleted_at":"2017-03-15 14:55:49",
        "deleted":1,
        "id":"b849891e-5904-4923-9aae-06b8a6a59f9d",
        "volume_id":"4941f9eb-f36b-4f66-9e51-c453f388771a",
        "attached_host":"prime-72",
        "instance_uuid":"112512cc-7cb3-42f6-afce-f0052170c53e",
        "mountpoint":"vda",
        "attach_time":"2014-10-29 19:06:54",
        "detach_time":"2017-03-15 14:55:49",
        "attach_mode":"rw",
        "attach_status":"detached"
    },
    {
        "created_at":"2015-08-20 12:14:19",
        "updated_at":"2015-08-26 16:45:32",
        "deleted_at":"2017-03-15 14:55:49",
        "deleted":1,
        "id":"ba39f6f5-57d6-4e90-a30d-d42a393f5179",
        "volume_id":"2f2cb4d0-ae3e-468e-a16f-2878ecf938cf",
        "attached_host":"prime-72",
        "instance_uuid":"09e54760-f43b-4213-99f8-46f584df34cb",
        "mountpoint":"vda",
        "attach_time":"2014-10-28 15:36:03",
        "detach_time":"2017-03-15 14:55:49",
        "attach_mode":"rw",
        "attach_status":"detached"
    },
    {
        "created_at":"2015-08-20 12:14:19",
        "updated_at":"2016-01-22 18:59:07",
        "deleted_at":"2017-03-15 14:55:49",
        "deleted":"@@@_3",
        "id":"bb36b8fd-38f8-4e15-916f-c854deca2cd9",
        "volume_id":"87f2eafb-71b1-4f03-8b40-58122a4fb078",
        "attached_host":"prime-72",
        "instance_uuid":"e6d5dad2-388f-4aa9-9bfd-4b0501246183",
        "mountpoint":"vda",
        "attach_time":"2014-12-08 18:06:43",
        "detach_time":"2017-03-15 14:55:49",
        "attach_mode":"rw",
        "attach_status":"detached"
    },
    {
        "created_at":"2015-08-20 12:14:19",
        "updated_at":"2016-12-08 15:38:53",
        "deleted_at":"2017-03-15 14:55:49",
        "deleted":1,
        "id":"bbc9d278-c722-43f3-b09d-2f4541f3c4f3",
        "volume_id":"070dd704-83ea-42c9-82f5-79b876e3cf86",
        "attached_host":"flare-zenit3",
        "instance_uuid":"4ef1868c-5440-4799-8743-8d719e5f2d80",
        "mountpoint":"\/dev\/vdc",
        "attach_time":"2015-01-30 00:35:00",
        "detach_time":"2017-03-15 14:55:49",
        "attach_mode":"rw",
        "attach_status":"detached"
    },
    {
        "created_at":"2015-08-20 12:14:19",
        "updated_at":"2016-01-20 21:00:00",
        "deleted_at":"2017-03-15 14:55:49",
        "deleted":"@@@_0",
        "id":"c0bc5c0c-f752-4c9b-935b-45bf94ecff5d",
        "volume_id":"d020a66e-acef-4609-90a3-6c52166d97ec",
        "attached_host":"prime-72",
        "instance_uuid":"16fb6075-5e56-4d5b-8792-27068af9df76",
        "mountpoint":"vda",
        "attach_time":"2014-09-09 14:01:07",
        "detach_time":"2017-03-15 14:55:49",
        "attach_mode":"rw",
        "attach_status":"detached"
    },
    {
        "created_at":"2015-08-20 12:14:19",
        "updated_at":"2016-06-08 15:24:01",
        "deleted_at":"2017-03-15 14:55:49",
        "deleted":"@@@_2",
        "id":"c5f42893-ff58-4cb9-b799-6d86c2aa8ee5",
        "volume_id":"ffe40ffa-6fec-4a18-83ae-bc32d08dd184",
        "attached_host":"blitz7-83",
        "instance_uuid":"698f701b-c4c8-4eb4-89ce-bde03e970f2b",
        "mountpoint":"\/dev\/vda",
        "attach_time":"2015-06-01 20:10:41",
        "detach_time":"2017-03-15 14:55:49",
        "attach_mode":"rw",
        "attach_status":"detached"
    },
    {
        "created_at":"2015-08-20 12:14:19",
        "updated_at":"2015-11-20 15:55:41",
        "deleted_at":"2017-03-15 14:55:49",
        "deleted":1,
        "id":"c86b4271-4afd-443b-ae2f-46dac1d61522",
        "volume_id":"db4bdc5c-08dd-4987-a886-e3cb1a23dcb4",
        "attached_host":"blitz7-83",
        "instance_uuid":"4284fea0-b41f-47d3-805a-b49600cb8aaa",
        "mountpoint":"\/dev\/vdb",
        "attach_time":"2015-07-16 19:46:58",
        "detach_time":"2017-03-15 14:55:49",
        "attach_mode":"rw",
        "attach_status":"detached"
    },
    {
        "created_at":"2015-08-20 12:14:19",
        "updated_at":"2016-01-11 21:17:39",
        "deleted_at":"2017-03-15 14:55:49",
        "deleted":"@@@_0",
        "id":"cc68d3c8-ef42-4a32-8469-6d7324998346",
        "volume_id":"9dd9febf-7d3c-4115-8002-05a7ae072dc4",
        "attached_host":"prime-72",
        "instance_uuid":"d7eb2fc4-3b77-4b4a-bf18-01fb32501563",
        "mountpoint":"vda",
        "attach_time":"2014-03-29 21:34:09",
        "detach_time":"2017-03-15 14:55:49",
        "attach_mode":"rw",
        "attach_status":"detached"
    },
    {
        "created_at":"2015-08-20 12:14:19",
        "updated_at":"2016-01-25 15:21:30",
        "deleted_at":"2017-03-15 14:55:49",
        "deleted":1,
        "id":"d182b37c-35ef-4ce9-8f38-7874956643bd",
        "volume_id":"3a8da1ee-c127-417a-8829-c60bcd96bb65",
        "attached_host":"prime-72",
        "instance_uuid":"d7a54a6c-a923-454c-9237-017256476311",
        "mountpoint":"vda",
        "attach_time":"2014-09-19 15:52:29",
        "detach_time":"2017-03-15 14:55:49",
        "attach_mode":"rw",
        "attach_status":"detached"
    },
    {
        "created_at":"2015-08-20 12:14:19",
        "updated_at":"2016-01-25 15:21:32",
        "deleted_at":"2017-03-15 14:55:49",
        "deleted":1,
        "id":"d2345554-0526-4cff-a406-aad556b753c9",
        "volume_id":"838ff31b-3e17-49f9-b99e-4e1ba47b701c",
        "attached_host":"prime-72",
        "instance_uuid":"a5e471fa-bc80-4bb4-8ece-aefd7fcda9a1",
        "mountpoint":"vda",
        "attach_time":"2014-10-23 22:36:27",
        "detach_time":"2017-03-15 14:55:49",
        "attach_mode":"rw",
        "attach_status":"detached"
    },
    {
        "created_at":"2015-08-20 12:14:19",
        "updated_at":"2016-09-26 17:55:34",
        "deleted_at":"2017-03-15 14:55:49",
        "deleted":"@@@_3",
        "id":"d48d94b7-6413-4951-b0dd-399a0a2a4da2",
        "volume_id":"6421eb49-1c25-4308-a61e-2a3a0aeeb49e",
        "attached_host":"flare-zenit3",
        "instance_uuid":"8266b2a0-ab0f-4f1b-a63d-9c9a3651bc24",
        "mountpoint":"\/dev\/vdb",
        "attach_time":"2015-05-28 14:41:03",
        "detach_time":"2017-03-15 14:55:49",
        "attach_mode":"rw",
        "attach_status":"detached"
    },
    {
        "created_at":"2015-08-20 12:14:19",
        "updated_at":"2016-01-31 22:13:16",
        "deleted_at":"2017-03-15 14:55:49",
        "deleted":"@@@_0",
        "id":"d620c546-2550-46a7-b67c-b4ec63a3e050",
        "volume_id":"2f3a41a0-efa3-49b3-838a-8276191be18f",
        "attached_host":"blitz7-83",
        "instance_uuid":"7253d2a9-5673-4a6d-b10d-f368e95278c1",
        "mountpoint":"\/dev\/vda",
        "attach_time":"2015-08-13 02:01:56",
        "detach_time":"2017-03-15 14:55:49",
        "attach_mode":"rw",
        "attach_status":"detached"
    },
    {
        "created_at":"2015-08-20 12:14:19",
        "updated_at":"2016-10-28 18:33:41",
        "deleted_at":"2017-03-15 14:55:49",
        "deleted":1,
        "id":"d6b73e23-eeed-48be-b226-fdc22b1c4214",
        "volume_id":"ba2852c5-43e0-412e-a1b1-bd2b5fa10318",
        "attached_host":"blitz7-83",
        "instance_uuid":"bb39c5ef-0726-4701-80a0-7991cb7ac814",
        "mountpoint":"\/dev\/vda",
        "attach_time":"2015-06-13 02:30:26",
        "detach_time":"2017-03-15 14:55:49",
        "attach_mode":"rw",
        "attach_status":"detached"
    },
    {
        "created_at":"2015-08-20 12:14:19",
        "updated_at":"2015-11-10 23:08:26",
        "deleted_at":"2017-03-15 14:55:49",
        "deleted":"@@@_2",
        "id":"d6d2ee98-43c1-40b0-bfd4-235000169e80",
        "volume_id":"72f24553-6bca-4e9b-96a6-dd06c6333a65",
        "attached_host":"prime-72",
        "instance_uuid":"33bd02d8-88dd-4186-b2f2-c90e698051bc",
        "mountpoint":"\/dev\/vda",
        "attach_time":"2015-05-15 18:41:04",
        "detach_time":"2017-03-15 14:55:49",
        "attach_mode":"rw",
        "attach_status":"detached"
    },
    {
        "created_at":"2015-08-20 12:14:19",
        "updated_at":"2016-01-12 20:01:12",
        "deleted_at":"2017-03-15 14:55:49",
        "deleted":1,
        "id":"d75254ea-bddd-4d75-b8c9-dc25306285ac",
        "volume_id":"1f42fd26-05b6-4173-a750-40e0c2b3da07",
        "attached_host":"prime-72",
        "instance_uuid":"86ec50f6-0cc7-4923-b0b3-05ef93e27efe",
        "mountpoint":"\/dev\/vda",
        "attach_time":"2015-02-26 00:38:13",
        "detach_time":"2017-03-15 14:55:49",
        "attach_mode":"rw",
        "attach_status":"detached"
    },
    {
        "created_at":"2015-08-20 12:14:19",
        "updated_at":"2015-12-02 22:35:09",
        "deleted_at":"2017-03-15 14:55:49",
        "deleted":"@@@_0",
        "id":"dbc1d91f-5db9-42a2-ad99-0eac096032ae",
        "volume_id":"efaaa72c-123b-4530-b9a9-a445a673a901",
        "attached_host":"prime-72",
        "instance_uuid":"ba4014ff-ed7b-44d5-8c05-aacb3b384948",
        "mountpoint":"\/dev\/vda",
        "attach_time":"2015-05-15 18:39:42",
        "detach_time":"2017-03-15 14:55:49",
        "attach_mode":"rw",
        "attach_status":"detached"
    },
    {
        "created_at":"2015-08-20 12:14:19",
        "updated_at":"2015-10-19 22:06:24",
        "deleted_at":"2017-03-15 14:55:49",
        "deleted":1,
        "id":"dcab6127-e395-4fab-86d4-3cf5a0a94492",
        "volume_id":"fdca23eb-7f58-4fe7-bf43-a310f1e3cff0",
        "attached_host":"blitz7-83",
        "instance_uuid":"1756db44-0570-471d-9769-915ff9db26c6",
        "mountpoint":"\/dev\/vda",
        "attach_time":"2015-06-24 21:34:05",
        "detach_time":"2017-03-15 14:55:49",
        "attach_mode":"rw",
        "attach_status":"detached"
    },
    {
        "created_at":"2015-08-20 12:14:19",
        "updated_at":"2016-01-21 14:58:24",
        "deleted_at":"2017-03-15 14:55:49",
        "deleted":1,
        "id":"de05536a-c69a-4922-a660-8b1fa5d9eaeb",
        "volume_id":"4b2bf8fd-2ae2-4fb9-a33d-1cd657c5833f",
        "attached_host":"prime-72",
        "instance_uuid":"91712328-e495-4810-af2f-3608d2d3a281",
        "mountpoint":"vda",
        "attach_time":"2014-12-11 20:15:13",
        "detach_time":"2017-03-15 14:55:49",
        "attach_mode":"rw",
        "attach_status":"detached"
    },
    {
        "created_at":"2015-08-20 12:14:19",
        "updated_at":"2015-12-09 19:33:54",
        "deleted_at":"2017-03-15 14:55:49",
        "deleted":"@@@_0",
        "id":"e03c33c2-6680-4b69-9955-900e67df974f",
        "volume_id":"679549c1-b8a9-47bf-a639-4a64f8f39ef8",
        "attached_host":"prime-72",
        "instance_uuid":"e1797521-316f-4005-abbe-78e566aa2a54",
        "mountpoint":"vda",
        "attach_time":"2014-06-09 13:07:27",
        "detach_time":"2017-03-15 14:55:49",
        "attach_mode":"rw",
        "attach_status":"detached"
    },
    {
        "created_at":"2015-08-20 12:14:19",
        "updated_at":"2015-08-24 14:14:30",
        "deleted_at":"2017-03-15 14:55:49",
        "deleted":1,
        "id":"e162980a-be38-4c31-8755-5e3327b8263b",
        "volume_id":"776e2367-1981-4ae5-b5b0-aeb9a936dca6",
        "attached_host":"blitz7-83",
        "instance_uuid":"f832ce7d-a60c-45e1-9246-60ae7320e556",
        "mountpoint":"\/dev\/vda",
        "attach_time":"2015-06-18 15:58:21",
        "detach_time":"2017-03-15 14:55:49",
        "attach_mode":"rw",
        "attach_status":"detached"
    },
    {
        "created_at":"2015-08-20 12:14:19",
        "updated_at":"2016-01-15 15:44:54",
        "deleted_at":"2017-03-15 14:55:49",
        "deleted":"@@@_2",
        "id":"e276ad3f-6574-4ce3-90f0-e65c9a9173e0",
        "volume_id":"46876237-8bb7-4e2a-a1f6-8e7b296fdcad",
        "attached_host":"prime-72",
        "instance_uuid":"d33b3743-4ca0-429c-92c1-7160b5c3db9e",
        "mountpoint":"\/dev\/vdb",
        "attach_time":"2014-12-05 22:44:24",
        "detach_time":"2017-03-15 14:55:49",
        "attach_mode":"rw",
        "attach_status":"detached"
    },
    {
        "created_at":"2015-08-20 12:14:19",
        "updated_at":"2016-03-31 17:39:06",
        "deleted_at":"2017-03-15 14:55:49",
        "deleted":1,
        "id":"e3bbd110-63c0-4a2e-a0a3-9c204e7f4a0f",
        "volume_id":"f542c126-9234-4db6-92e4-70211729aec7",
        "attached_host":"blitz7-83",
        "instance_uuid":"e3a044a4-ef87-4e26-9874-264e4f3dd19d",
        "mountpoint":"\/dev\/vdb",
        "attach_time":"2015-07-14 01:39:40",
        "detach_time":"2017-03-15 14:55:49",
        "attach_mode":"rw",
        "attach_status":"detached"
    },
    {
        "created_at":"2015-08-20 12:14:19",
        "updated_at":"2016-01-19 21:46:51",
        "deleted_at":"2017-03-15 14:55:49",
        "deleted":"@@@_0",
        "id":"e45b12ad-092d-4c29-89ba-4b8e5dad34cb",
        "volume_id":"ef7e9de1-ca1c-41f1-923d-784fda2aa6ae",
        "attached_host":"prime-72",
        "instance_uuid":"2c890508-1e7c-4e55-812f-4ad7642cb170",
        "mountpoint":"vda",
        "attach_time":"2014-12-05 18:12:47",
        "detach_time":"2017-03-15 14:55:49",
        "attach_mode":"rw",
        "attach_status":"detached"
    },
    {
        "created_at":"2015-08-20 12:14:19",
        "updated_at":"2016-01-11 21:22:39",
        "deleted_at":"2017-03-15 14:55:49",
        "deleted":1,
        "id":"e56cc8ff-4f02-48b8-ad8b-23e897b6be69",
        "volume_id":"794c3ff5-2af2-453c-a5f4-8ea6845b42cf",
        "attached_host":"prime-72",
        "instance_uuid":"1b276042-95e8-4644-b013-65e0447f6fe9",
        "mountpoint":"\/dev\/vda",
        "attach_time":"2015-04-14 14:40:13",
        "detach_time":"2017-03-15 14:55:49",
        "attach_mode":"rw",
        "attach_status":"detached"
    },
    {
        "created_at":"2015-08-20 12:14:19",
        "updated_at":"2016-01-20 19:00:20",
        "deleted_at":"2017-03-15 14:55:49",
        "deleted":"@@@_2",
        "id":"ec50dcee-815e-458e-a81c-793603a44a6a",
        "volume_id":"40ee11da-430e-491b-ba52-51dd21e4b3a9",
        "attached_host":"prime-72",
        "instance_uuid":"d02a37b0-c3e2-440a-a098-e5cb78b13cd6",
        "mountpoint":"vda",
        "attach_time":"2015-01-13 19:31:25",
        "detach_time":"2017-03-15 14:55:49",
        "attach_mode":"rw",
        "attach_status":"detached"
    },
    {
        "created_at":"2015-08-20 12:14:19",
        "updated_at":"2015-12-22 23:36:05",
        "deleted_at":"2017-03-15 14:55:49",
        "deleted":"@@@_2.0",
        "id":"ed62b75f-d350-434e-bcc9-8441ba5e5538",
        "volume_id":"98e4f3cb-32d8-4fb8-b413-df5883c323e2",
        "attached_host":"prime-72",
        "instance_uuid":"2e65616c-c0c5-466c-8ac3-e06a61fe847a",
        "mountpoint":"vda",
        "attach_time":"2014-08-08 19:12:13",
        "detach_time":"2017-03-15 14:55:49",
        "attach_mode":"rw",
        "attach_status":"detached"
    },
    {
        "created_at":"2015-08-20 12:14:19",
        "updated_at":"2016-01-20 22:07:15",
        "deleted_at":"2017-03-15 14:55:49",
        "deleted":"@@@_0.0",
        "id":"ed76d2a5-1053-4748-8294-96c1bf99d2bf",
        "volume_id":"f439574f-55ee-439c-86f1-7cfe2d0baa34",
        "attached_host":"prime-72",
        "instance_uuid":"0b413220-ca75-482c-8050-3b0524365e9d",
        "mountpoint":"vda",
        "attach_time":"2014-03-11 20:04:45",
        "detach_time":"2017-03-15 14:55:49",
        "attach_mode":"rw",
        "attach_status":"detached"
    },
    {
        "created_at":"2015-08-20 12:14:19",
        "updated_at":"2015-12-25 19:53:47",
        "deleted_at":"2017-03-15 14:55:49",
        "deleted":"@@@_-1.0",
        "id":"eec38170-7d1a-4fb1-a69c-003a5e0059ba",
        "volume_id":"546d271c-1fb1-4e68-a3e9-66e4a8fca9e3",
        "attached_host":"prime-72",
        "instance_uuid":"ec741654-d760-4916-9972-6b6c241f63e0",
        "mountpoint":"vda",
        "attach_time":"2015-01-14 04:54:59",
        "detach_time":"2017-03-15 14:55:49",
        "attach_mode":"rw",
        "attach_status":"detached"
    },
    {
        "created_at":"2015-08-20 12:14:19",
        "updated_at":"2016-01-25 15:21:34",
        "deleted_at":"2017-03-15 14:55:49",
        "deleted":"@@@_1.5",
        "id":"ef331b72-917b-4aac-93cc-f8601969bc6a",
        "volume_id":"b47bc5b1-ee7d-4023-ac7e-2e00496055a8",
        "attached_host":"prime-72",
        "instance_uuid":"09d16e3f-aaa6-4642-a661-586a1039b9ba",
        "mountpoint":"vda",
        "attach_time":"2014-08-27 02:03:53",
        "detach_time":"2017-03-15 14:55:49",
        "attach_mode":"rw",
        "attach_status":"detached"
    },
    {
        "created_at":"2015-08-20 12:14:19",
        "updated_at":"2016-06-15 17:17:19",
        "deleted_at":"2017-03-15 14:55:49",
        "deleted":1.0,
        "id":"f2ff669c-81a3-4d97-b4de-4315f465ea75",
        "volume_id":"6f8bf3c7-a7a3-451d-a4c7-6402408f921e",
        "attached_host":"blitz7-83",
        "instance_uuid":"929a66f5-593a-42d0-b2ea-9e3c8e54eb7c",
        "mountpoint":"\/dev\/vda",
        "attach_time":"2015-06-17 22:46:41",
        "detach_time":"2017-03-15 14:55:49",
        "attach_mode":"rw",
        "attach_status":"detached"
    },
    {
        "created_at":"2015-08-20 12:14:19",
        "updated_at":"2015-12-22 23:36:07",
        "deleted_at":"2017-03-15 14:55:49",
        "deleted":1.0,
        "id":"f3dbfa43-070b-499a-a657-d1dec8ea1657",
        "volume_id":"bd808141-8e19-4e3e-9956-7944107e34c5",
        "attached_host":"prime-72",
        "instance_uuid":"2e65616c-c0c5-466c-8ac3-e06a61fe847a",
        "mountpoint":"\/dev\/vdb",
        "attach_time":"2014-08-08 21:14:16",
        "detach_time":"2017-03-15 14:55:49",
        "attach_mode":"rw",
        "attach_status":"detached"
    },
    {
        "created_at":"2015-08-20 12:14:19",
        "updated_at":"2016-01-25 15:23:07",
        "deleted_at":"2017-03-15 14:55:49",
        "deleted":1.0,
        "id":"f417c49e-ac45-4d54-949f-177a57a10b68",
        "volume_id":"9cc29c97-be55-474f-a50d-53fbfbaa17ba",
        "attached_host":"prime-72",
        "instance_uuid":"8bf7fefa-a644-41b3-b060-8197f926b109",
        "mountpoint":"\/dev\/vdb",
        "attach_time":"2014-12-03 20:40:30",
        "detach_time":"2017-03-15 14:55:49",
        "attach_mode":"rw",
        "attach_status":"detached"
    },
    {
        "created_at":"2015-08-20 12:14:19",
        "updated_at":"2015-09-30 23:15:13",
        "deleted_at":"2017-03-15 14:55:49",
        "deleted":1.0,
        "id":"f713c7d5-e099-4f23-b594-10f54e90abf8",
        "volume_id":"10321520-1454-4cb8-bcf5-cb6f42648e4e",
        "attached_host":"blitz7-83",
        "instance_uuid":"d89e9e1d-e4aa-4e41-8644-d2dfae816dce",
        "mountpoint":"\/dev\/vda",
        "attach_time":"2015-05-29 02:49:19",
        "detach_time":"2017-03-15 14:55:49",
        "attach_mode":"rw",
        "attach_status":"detached"
    },
    {
        "created_at":"2015-08-20 12:14:19",
        "updated_at":"2015-12-03 15:21:40",
        "deleted_at":"2017-03-15 14:55:49",
        "deleted":1.0,
        "id":"f7242e3b-8b3f-410b-9920-72ee79225787",
        "volume_id":"f4a1f24a-202f-40bb-ad10-942f1208934a",
        "attached_host":"prime-72",
        "instance_uuid":"a374f9ff-f115-4748-8051-731e725a05ec",
        "mountpoint":"vda",
        "attach_time":"2014-08-13 19:02:12",
        "detach_time":"2017-03-15 14:55:49",
        "attach_mode":"rw",
        "attach_status":"detached"
    },
    {
        "created_at":"2015-08-20 12:14:19",
        "updated_at":"2015-09-11 11:30:35",
        "deleted_at":"2017-03-15 14:55:49",
        "deleted":1.0,
        "id":"f92765bc-f74b-43cc-8d3f-5e25a1030f6e",
        "volume_id":"5311132f-0908-4878-9128-65d45413662f",
        "attached_host":"blitz7-83",
        "instance_uuid":"520a7bc9-ae32-43f1-8cbf-34a3f3cb08e0",
        "mountpoint":"\/dev\/vdb",
        "attach_time":"2015-08-11 12:27:51",
        "detach_time":"2017-03-15 14:55:49",
        "attach_mode":"rw",
        "attach_status":"detached"
    },
    {
        "created_at":"2015-08-20 12:14:19",
        "updated_at":"2016-01-19 16:16:30",
        "deleted_at":"2017-03-15 14:55:49",
        "deleted":1.0,
        "id":"fe3d5204-efde-44b7-baad-f5e5885a1fad",
        "volume_id":"b3addbf7-bb04-4345-b9b3-29715b51efe1",
        "attached_host":"blitz7-83",
        "instance_uuid":"cde9e2e7-fa2a-4825-ac6a-4a31eb1e2e66",
        "mountpoint":"\/dev\/vda",
        "attach_time":"2015-06-01 13:29:19",
        "detach_time":"2017-03-15 14:55:49",
        "attach_mode":"rw",
        "attach_status":"detached"
    },
    {
        "created_at":"2015-08-20 12:14:19",
        "updated_at":"2015-09-27 18:50:35",
        "deleted_at":"2017-03-15 14:55:49",
        "deleted":1.0,
        "id":"fffdbe39-69f9-42ac-84fe-4784c88e2cbc",
        "volume_id":"e44c1640-2857-425e-a013-e24d96f0e76f",
        "attached_host":"flare-zenit3",
        "instance_uuid":"dbdd3055-2841-45b2-84c3-aee2d0d3cbc1",
        "mountpoint":"\/dev\/vdb",
        "attach_time":"2014-12-13 19:08:16",
        "detach_time":"2017-03-15 14:55:49",
        "attach_mode":"rw",
        "attach_status":"detached"
    }
]